uz_ai/__init__.py
uz_ai-0.0.2.dist-info/METADATA
uz_ai-0.0.2.dist-info/WHEEL
uz_ai-0.0.2.dist-info/top_level.txt
uz_ai-0.0.2.dist-info/RECORD
