Metadata-Version: 2.1
Name: uz_ai
Version: 0.0.2
Summary: siz UzAi da sun'iy intelektlar yarata olasiz
Home-page: https://github.com/UzCoder123
Author: Salohiddin Esanbekov
Author-email: email@manzil.com
Classifier: Programming Language :: Python :: 3
Classifier: License :: OSI Approved :: MIT License
Classifier: Operating System :: OS Independent
Requires-Python: >=3.8
